covers-0.0.4.dist-info/METADATA
covers-0.0.4.dist-info/WHEEL
covers-0.0.4.dist-info/entry_points.txt
covers-0.0.4.dist-info/licenses/LICENSE
covers/__init__.py
covers/__main__.py
covers/branch.py
covers/covers.py
covers/covers_core.abi3.so
covers/importer.py
covers/runner.py
covers/schemas.py
covers-0.0.4.dist-info/RECORD
