Metadata-Version: 2.4
Name: covers
Version: 0.0.4
Classifier: License :: OSI Approved :: Apache Software License
Classifier: Operating System :: MacOS :: MacOS X
Classifier: Operating System :: Microsoft :: Windows :: Windows 10
Classifier: Operating System :: POSIX :: Linux
Classifier: Programming Language :: Python :: 3.12
Classifier: Programming Language :: Python :: 3.13
Classifier: Programming Language :: Python :: 3.14
License-File: LICENSE
Summary: Near Zero-Overhead Python Code Coverage
Keywords: coverage,testing
Requires-Python: >=3.12, <3.15
Project-URL: Homepage, https://github.com/amartani/covers
Project-URL: Repository, https://github.com/amartani/covers
